{
  "videos": [
    {
      "id": "7610398705572763307",
      "authorName": "晚安小公主",
      "title": "酸角粥陪丸看看我#三角洲 #三角洲女玩家",
      "playCount": 1902,
      "delta": 16,
      "publishAt": "2026/02/24 19:53:52",
      "url": "https://www.douyin.com/video/7610398705572763307"
    },
    {
      "id": "7604449211664487282",
      "authorName": "小小舟",
      "title": "陪玩日记：每天都有试不完的音，但就是选不到我#三角洲行动 #三角洲 #三角洲陪玩",
      "playCount": 4501,
      "delta": 7,
      "publishAt": "2026/02/08 19:06:46",
      "url": "https://www.douyin.com/video/7604449211664487282"
    },
    {
      "id": "7615944159149737801",
      "authorName": "奈奈酱紫",
      "title": "哥哥 猛攻吗#三角洲 #三角洲行动",
      "playCount": 179,
      "delta": 5,
      "publishAt": "2026/03/11 18:33:01",
      "url": "https://www.douyin.com/video/7615944159149737801"
    },
    {
      "id": "7616360633298980337",
      "authorName": "妮妮（三角洲主页",
      "title": "三角洲陪。#三角洲 #三角洲行动 #三角洲陪玩",
      "playCount": 41,
      "delta": 0,
      "publishAt": "2026/03/12 21:29:09",
      "url": "https://www.douyin.com/video/7616360633298980337"
    },
    {
      "id": "7616009419432987002",
      "authorName": "朵朵（三角洲主页",
      "title": "三角洲。#三角洲行动 #三角洲陪玩 #三角洲女陪 #三角洲",
      "playCount": 307,
      "delta": 0,
      "publishAt": "2026/03/11 22:46:16",
      "url": "https://www.douyin.com/video/7616009419432987002"
    },
    {
      "id": "7613832689694923194",
      "authorName": "甜甜owo（三角洲主页",
      "title": "三角洲陪 #三角洲 #三角洲行动 #三角洲陪玩",
      "playCount": 156,
      "delta": 0,
      "publishAt": "2026/03/06 01:59:27",
      "url": "https://www.douyin.com/video/7613832689694923194"
    },
    {
      "id": "7614918796037845369",
      "authorName": "困困小瑜（陪丸看煮页）",
      "title": "三角洲女玩家三角洲女玩家 #三角洲 #三角洲行动 #三角洲陪玩",
      "playCount": 481,
      "delta": 0,
      "publishAt": "2026/03/09 00:14:05",
      "url": "https://www.douyin.com/video/7614918796037845369"
    },
    {
      "id": "7614863419133256825",
      "authorName": "小美 （?煮?）",
      "title": "三角洲行动三角洲行动 #三角洲行动 #三角洲陪玩 #三角洲 #三角洲女陪",
      "playCount": 572,
      "delta": 0,
      "publishAt": "2026/03/08 20:39:11",
      "url": "https://www.douyin.com/video/7614863419133256825"
    },
    {
      "id": "7614916918022289253",
      "authorName": "甜甜owo（三角洲主页",
      "title": "三角洲女玩家。#三角洲 #三角洲行动 #三角洲陪玩",
      "playCount": 746,
      "delta": 0,
      "publishAt": "2026/03/09 00:06:48",
      "url": "https://www.douyin.com/video/7614916918022289253"
    },
    {
      "id": "7616176662350884261",
      "authorName": "小桃桃?",
      "title": "有谁陪我打三角洲啊！鼠鼠公主启动了 有谁陪我！#玩游戏我是认真的 #三角洲行动 #三角洲女玩家 #三角洲陪玩 #三角洲技术",
      "playCount": 29,
      "delta": 0,
      "publishAt": "2026/03/12 09:35:14",
      "url": "https://www.douyin.com/video/7616176662350884261"
    }
  ],
  "updateTime": 1773388826000
}